mrakun
