Metadata-Version: 1.0
Name: mrakun
Version: 0.44
Summary: Rank-based unsupervised keyword detection via metavertex aggregation
Home-page: http://github.com/skblaz/mrakun
Author: Blaž Škrlj
Author-email: blaz.skrlj@ijs.si
License: GPL3
Platform: UNKNOWN
